racebert/__init__.py
racebert-1.1.0.dist-info/METADATA
racebert-1.1.0.dist-info/WHEEL
racebert-1.1.0.dist-info/top_level.txt
racebert-1.1.0.dist-info/RECORD
