Metadata-Version: 2.1
Name: racebert
Version: 1.1.0
Summary: Race and Ethnicity Prediction from names
Home-page: https://github.com/parasurama/raceBERT
Author: Prasanna Parasurama
Author-email: pparasurama@gmail.com
License: MIT
Platform: UNKNOWN
Classifier: License :: OSI Approved :: MIT License
Classifier: Programming Language :: Python :: 3
Classifier: Programming Language :: Python :: 3.8
Requires-Dist: transformers
